{
    "gameTimeSeconds": 3855.5337,
    "gameWinner": 2,
    "fbBeforeHorn": false,
    "fbAfter10min": false,
    "isRampageInGame": false,
    "lessThan25min": false,
    "leagueId": 17418,
    "playerInfo": [
        {
            "name": "Nightfall",
            "steamId": 76561198085066985,
            "kills": 13,
            "deaths": 2,
            "assists": 4,
            "selectedHeroId": 19,
            "pickOrder": 10,
            "teamfightParticipation": 0.68,
            "heroTierDotaPlus": 5850,
            "firstBloodClaimed": false,
            "runes": 8,
            "gpm": 838.6076,
            "teamNum": 2,
            "isWon": true,
            "lastHits": 745,
            "towerKills": 8,
            "wardsPlaced": 0,
            "campsStacked": 0,
            "watchersTaken": 2,
            "smokesUsed": 0,
            "lotusesGrabbed": 2,
            "roshanKills": 2,
            "stuns": 65.633125,
            "tormentorKills": 2,
            "courierKills": 0,
            "networth": 53888,
            "madstonesCollected": 45,
            "isFirstPick": false,
            "isLastPick": true,
            "isMasterGrandMaster": false,
            "lastGameOfTheSeries": true,
            "theMostDeaths": false,
            "theMostAssists": false,
            "theLowestNetworth": false,
            "noKills": false,
            "isBoughtBackBefore30": false
        },
        {
            "name": "kiyotaka",
            "steamId": 76561198818372174,
            "kills": 7,
            "deaths": 3,
            "assists": 6,
            "selectedHeroId": 114,
            "pickOrder": 4,
            "teamfightParticipation": 0.52,
            "heroTierDotaPlus": 2749,
            "firstBloodClaimed": false,
            "runes": 20,
            "gpm": 679.3301,
            "teamNum": 2,
            "isWon": true,
            "lastHits": 577,
            "towerKills": 3,
            "wardsPlaced": 1,
            "campsStacked": 0,
            "watchersTaken": 8,
            "smokesUsed": 0,
            "lotusesGrabbed": 6,
            "roshanKills": 1,
            "stuns": 69.53227,
            "tormentorKills": 2,
            "courierKills": 0,
            "networth": 43653,
            "madstonesCollected": 45,
            "isFirstPick": false,
            "isLastPick": false,
            "isMasterGrandMaster": false,
            "lastGameOfTheSeries": true,
            "theMostDeaths": false,
            "theMostAssists": false,
            "theLowestNetworth": false,
            "noKills": false,
            "isBoughtBackBefore30": false
        },
        {
            "name": "TORONTOTOKYO",
            "steamId": 76561198392036633,
            "kills": 3,
            "deaths": 1,
            "assists": 14,
            "selectedHeroId": 55,
            "pickOrder": 2,
            "teamfightParticipation": 0.68,
            "heroTierDotaPlus": 1500,
            "firstBloodClaimed": true,
            "runes": 6,
            "gpm": 648.4705,
            "teamNum": 2,
            "isWon": true,
            "lastHits": 545,
            "towerKills": 0,
            "wardsPlaced": 0,
            "campsStacked": 5,
            "watchersTaken": 5,
            "smokesUsed": 0,
            "lotusesGrabbed": 2,
            "roshanKills": 1,
            "stuns": 32.564728,
            "tormentorKills": 2,
            "courierKills": 0,
            "networth": 41670,
            "madstonesCollected": 45,
            "isFirstPick": true,
            "isLastPick": false,
            "isMasterGrandMaster": false,
            "lastGameOfTheSeries": true,
            "theMostDeaths": false,
            "theMostAssists": false,
            "theLowestNetworth": false,
            "noKills": false,
            "isBoughtBackBefore30": false
        },
        {
            "name": "Mira",
            "steamId": 76561198216422051,
            "kills": 0,
            "deaths": 4,
            "assists": 16,
            "selectedHeroId": 100,
            "pickOrder": 8,
            "teamfightParticipation": 0.64,
            "heroTierDotaPlus": 30750,
            "firstBloodClaimed": false,
            "runes": 5,
            "gpm": 312.67267,
            "teamNum": 2,
            "isWon": true,
            "lastHits": 92,
            "towerKills": 1,
            "wardsPlaced": 17,
            "campsStacked": 2,
            "watchersTaken": 10,
            "smokesUsed": 3,
            "lotusesGrabbed": 6,
            "roshanKills": 0,
            "stuns": 44.132282,
            "tormentorKills": 1,
            "courierKills": 3,
            "networth": 20092,
            "madstonesCollected": 45,
            "isFirstPick": false,
            "isLastPick": false,
            "isMasterGrandMaster": false,
            "lastGameOfTheSeries": true,
            "theMostDeaths": false,
            "theMostAssists": true,
            "theLowestNetworth": false,
            "noKills": true,
            "isBoughtBackBefore30": false
        },
        {
            "name": "panto",
            "steamId": 76561198069224497,
            "kills": 2,
            "deaths": 1,
            "assists": 16,
            "selectedHeroId": 68,
            "pickOrder": 5,
            "teamfightParticipation": 0.72,
            "heroTierDotaPlus": 41915,
            "firstBloodClaimed": false,
            "runes": 9,
            "gpm": 351.64,
            "teamNum": 2,
            "isWon": true,
            "lastHits": 101,
            "towerKills": 0,
            "wardsPlaced": 11,
            "campsStacked": 4,
            "watchersTaken": 13,
            "smokesUsed": 8,
            "lotusesGrabbed": 0,
            "roshanKills": 0,
            "stuns": 30.399931,
            "tormentorKills": 0,
            "courierKills": 0,
            "networth": 22596,
            "madstonesCollected": 45,
            "isFirstPick": false,
            "isLastPick": false,
            "isMasterGrandMaster": false,
            "lastGameOfTheSeries": true,
            "theMostDeaths": false,
            "theMostAssists": true,
            "theLowestNetworth": false,
            "noKills": false,
            "isBoughtBackBefore30": false
        },
        {
            "name": "Xm",
            "steamId": 76561198097395311,
            "kills": 1,
            "deaths": 6,
            "assists": 6,
            "selectedHeroId": 16,
            "pickOrder": 3,
            "teamfightParticipation": 0.6363636,
            "heroTierDotaPlus": 9785,
            "firstBloodClaimed": false,
            "runes": 12,
            "gpm": 483.26382,
            "teamNum": 3,
            "isWon": false,
            "lastHits": 568,
            "towerKills": 0,
            "wardsPlaced": 1,
            "campsStacked": 6,
            "watchersTaken": 10,
            "smokesUsed": 0,
            "lotusesGrabbed": 1,
            "roshanKills": 0,
            "stuns": 44.69937,
            "tormentorKills": 1,
            "courierKills": 1,
            "networth": 31054,
            "madstonesCollected": 45,
            "isFirstPick": false,
            "isLastPick": false,
            "isMasterGrandMaster": false,
            "lastGameOfTheSeries": true,
            "theMostDeaths": false,
            "theMostAssists": false,
            "theLowestNetworth": false,
            "noKills": false,
            "isBoughtBackBefore30": false
        },
        {
            "name": "Xxs",
            "steamId": 76561198090224486,
            "kills": 1,
            "deaths": 4,
            "assists": 6,
            "selectedHeroId": 96,
            "pickOrder": 9,
            "teamfightParticipation": 0.6363636,
            "heroTierDotaPlus": 15430,
            "firstBloodClaimed": false,
            "runes": 2,
            "gpm": 412.53433,
            "teamNum": 3,
            "isWon": false,
            "lastHits": 434,
            "towerKills": 1,
            "wardsPlaced": 1,
            "campsStacked": 1,
            "watchersTaken": 3,
            "smokesUsed": 0,
            "lotusesGrabbed": 1,
            "roshanKills": 0,
            "stuns": 54.565453,
            "tormentorKills": 1,
            "courierKills": 0,
            "networth": 26509,
            "madstonesCollected": 45,
            "isFirstPick": false,
            "isLastPick": false,
            "isMasterGrandMaster": false,
            "lastGameOfTheSeries": true,
            "theMostDeaths": false,
            "theMostAssists": false,
            "theLowestNetworth": false,
            "noKills": false,
            "isBoughtBackBefore30": false
        },
        {
            "name": "XinQ",
            "steamId": 76561198117741251,
            "kills": 3,
            "deaths": 4,
            "assists": 8,
            "selectedHeroId": 9,
            "pickOrder": 6,
            "teamfightParticipation": 0.90909094,
            "heroTierDotaPlus": 53595,
            "firstBloodClaimed": false,
            "runes": 3,
            "gpm": 291.01028,
            "teamNum": 3,
            "isWon": false,
            "lastHits": 193,
            "towerKills": 0,
            "wardsPlaced": 12,
            "campsStacked": 5,
            "watchersTaken": 11,
            "smokesUsed": 1,
            "lotusesGrabbed": 3,
            "roshanKills": 0,
            "stuns": 63.899597,
            "tormentorKills": 1,
            "courierKills": 0,
            "networth": 18700,
            "madstonesCollected": 45,
            "isFirstPick": false,
            "isLastPick": false,
            "isMasterGrandMaster": true,
            "lastGameOfTheSeries": true,
            "theMostDeaths": false,
            "theMostAssists": false,
            "theLowestNetworth": true,
            "noKills": false,
            "isBoughtBackBefore30": false
        },
        {
            "name": "poloson",
            "steamId": 76561198037170520,
            "kills": 1,
            "deaths": 8,
            "assists": 7,
            "selectedHeroId": 89,
            "pickOrder": 7,
            "teamfightParticipation": 0.6363636,
            "heroTierDotaPlus": 3049,
            "firstBloodClaimed": false,
            "runes": 6,
            "gpm": 335.58,
            "teamNum": 3,
            "isWon": false,
            "lastHits": 183,
            "towerKills": 0,
            "wardsPlaced": 14,
            "campsStacked": 1,
            "watchersTaken": 8,
            "smokesUsed": 10,
            "lotusesGrabbed": 7,
            "roshanKills": 0,
            "stuns": 72.80669,
            "tormentorKills": 0,
            "courierKills": 1,
            "networth": 21564,
            "madstonesCollected": 45,
            "isFirstPick": false,
            "isLastPick": false,
            "isMasterGrandMaster": false,
            "lastGameOfTheSeries": true,
            "theMostDeaths": true,
            "theMostAssists": false,
            "theLowestNetworth": false,
            "noKills": false,
            "isBoughtBackBefore30": false
        },
        {
            "name": "Ame",
            "steamId": 76561198859019881,
            "kills": 5,
            "deaths": 3,
            "assists": 5,
            "selectedHeroId": 53,
            "pickOrder": 1,
            "teamfightParticipation": 0.90909094,
            "heroTierDotaPlus": 22500,
            "firstBloodClaimed": false,
            "runes": 2,
            "gpm": 810.82935,
            "teamNum": 3,
            "isWon": false,
            "lastHits": 969,
            "towerKills": 1,
            "wardsPlaced": 0,
            "campsStacked": 9,
            "watchersTaken": 4,
            "smokesUsed": 0,
            "lotusesGrabbed": 0,
            "roshanKills": 0,
            "stuns": 47.934303,
            "tormentorKills": 0,
            "courierKills": 0,
            "networth": 52103,
            "madstonesCollected": 45,
            "isFirstPick": true,
            "isLastPick": false,
            "isMasterGrandMaster": false,
            "lastGameOfTheSeries": true,
            "theMostDeaths": false,
            "theMostAssists": false,
            "theLowestNetworth": false,
            "noKills": false,
            "isBoughtBackBefore30": false
        }
    ]
}