{
    "gameTimeSeconds": 1771.9667,
    "gameWinner": 2,
    "fbBeforeHorn": false,
    "fbAfter10min": false,
    "isRampageInGame": false,
    "lessThan25min": false,
    "leagueId": 18359,
    "playerInfo": [
        {
            "name": "33",
            "steamId": 76561198046964005,
            "kills": 12,
            "deaths": 1,
            "assists": 7,
            "selectedHeroId": 2,
            "pickOrder": 8,
            "teamfightParticipation": 0.7916667,
            "heroTierDotaPlus": 16425,
            "firstBloodClaimed": false,
            "runes": 0,
            "gpm": 694.144,
            "teamNum": 2,
            "isWon": true,
            "lastHits": 269,
            "towerKills": 1,
            "wardsPlaced": 0,
            "campsStacked": 4,
            "watchersTaken": 0,
            "smokesUsed": 0,
            "lotusesGrabbed": 0,
            "roshanKills": 0,
            "stuns": 39.16631,
            "tormentorKills": 1,
            "courierKills": 0,
            "networth": 20500,
            "madstonesCollected": 25,
            "isFirstPick": false,
            "isLastPick": false,
            "isMasterGrandMaster": false,
            "lastGameOfTheSeries": true,
            "theMostDeaths": false,
            "theMostAssists": false,
            "theLowestNetworth": false,
            "noKills": false,
            "isBoughtBackBefore30": false
        },
        {
            "name": "Whitemon",
            "steamId": 76561198097094819,
            "kills": 1,
            "deaths": 5,
            "assists": 18,
            "selectedHeroId": 85,
            "pickOrder": 3,
            "teamfightParticipation": 0.7916667,
            "heroTierDotaPlus": 22140,
            "firstBloodClaimed": true,
            "runes": 2,
            "gpm": 358.11057,
            "teamNum": 2,
            "isWon": true,
            "lastHits": 70,
            "towerKills": 0,
            "wardsPlaced": 8,
            "campsStacked": 2,
            "watchersTaken": 0,
            "smokesUsed": 1,
            "lotusesGrabbed": 1,
            "roshanKills": 0,
            "stuns": 0.0,
            "tormentorKills": 0,
            "courierKills": 0,
            "networth": 10576,
            "madstonesCollected": 25,
            "isFirstPick": false,
            "isLastPick": false,
            "isMasterGrandMaster": false,
            "lastGameOfTheSeries": true,
            "theMostDeaths": false,
            "theMostAssists": true,
            "theLowestNetworth": false,
            "noKills": false,
            "isBoughtBackBefore30": false
        },
        {
            "name": "Crystallis",
            "steamId": 76561198087883707,
            "kills": 4,
            "deaths": 0,
            "assists": 14,
            "selectedHeroId": 102,
            "pickOrder": 7,
            "teamfightParticipation": 0.75,
            "heroTierDotaPlus": 2749,
            "firstBloodClaimed": false,
            "runes": 1,
            "gpm": 710.43097,
            "teamNum": 2,
            "isWon": true,
            "lastHits": 307,
            "towerKills": 5,
            "wardsPlaced": 0,
            "campsStacked": 3,
            "watchersTaken": 0,
            "smokesUsed": 0,
            "lotusesGrabbed": 2,
            "roshanKills": 1,
            "stuns": 0.0,
            "tormentorKills": 1,
            "courierKills": 1,
            "networth": 20981,
            "madstonesCollected": 25,
            "isFirstPick": false,
            "isLastPick": false,
            "isMasterGrandMaster": false,
            "lastGameOfTheSeries": true,
            "theMostDeaths": false,
            "theMostAssists": false,
            "theLowestNetworth": false,
            "noKills": false,
            "isBoughtBackBefore30": false
        },
        {
            "name": "bzm",
            "steamId": 76561198053884305,
            "kills": 6,
            "deaths": 3,
            "assists": 13,
            "selectedHeroId": 39,
            "pickOrder": 10,
            "teamfightParticipation": 0.75,
            "heroTierDotaPlus": 63120,
            "firstBloodClaimed": false,
            "runes": 10,
            "gpm": 632.9577,
            "teamNum": 2,
            "isWon": true,
            "lastHits": 240,
            "towerKills": 0,
            "wardsPlaced": 3,
            "campsStacked": 4,
            "watchersTaken": 0,
            "smokesUsed": 0,
            "lotusesGrabbed": 1,
            "roshanKills": 0,
            "stuns": 0.0,
            "tormentorKills": 1,
            "courierKills": 0,
            "networth": 18693,
            "madstonesCollected": 25,
            "isFirstPick": false,
            "isLastPick": true,
            "isMasterGrandMaster": true,
            "lastGameOfTheSeries": true,
            "theMostDeaths": false,
            "theMostAssists": false,
            "theLowestNetworth": false,
            "noKills": false,
            "isBoughtBackBefore30": false
        },
        {
            "name": "Saksa",
            "steamId": 76561198064001473,
            "kills": 1,
            "deaths": 1,
            "assists": 15,
            "selectedHeroId": 19,
            "pickOrder": 4,
            "teamfightParticipation": 0.6666667,
            "heroTierDotaPlus": 28205,
            "firstBloodClaimed": false,
            "runes": 5,
            "gpm": 407.91965,
            "teamNum": 2,
            "isWon": true,
            "lastHits": 116,
            "towerKills": 0,
            "wardsPlaced": 3,
            "campsStacked": 2,
            "watchersTaken": 0,
            "smokesUsed": 1,
            "lotusesGrabbed": 5,
            "roshanKills": 0,
            "stuns": 46.828926,
            "tormentorKills": 1,
            "courierKills": 1,
            "networth": 12047,
            "madstonesCollected": 25,
            "isFirstPick": false,
            "isLastPick": false,
            "isMasterGrandMaster": false,
            "lastGameOfTheSeries": true,
            "theMostDeaths": false,
            "theMostAssists": false,
            "theLowestNetworth": false,
            "noKills": false,
            "isBoughtBackBefore30": false
        },
        {
            "name": "Jabz",
            "steamId": 76561198060737259,
            "kills": 2,
            "deaths": 4,
            "assists": 3,
            "selectedHeroId": 135,
            "pickOrder": 9,
            "teamfightParticipation": 0.5,
            "heroTierDotaPlus": 7050,
            "firstBloodClaimed": false,
            "runes": 0,
            "gpm": 449.26352,
            "teamNum": 3,
            "isWon": false,
            "lastHits": 244,
            "towerKills": 0,
            "wardsPlaced": 0,
            "campsStacked": 6,
            "watchersTaken": 0,
            "smokesUsed": 0,
            "lotusesGrabbed": 1,
            "roshanKills": 0,
            "stuns": 14.166138,
            "tormentorKills": 0,
            "courierKills": 0,
            "networth": 13268,
            "madstonesCollected": 25,
            "isFirstPick": false,
            "isLastPick": false,
            "isMasterGrandMaster": false,
            "lastGameOfTheSeries": true,
            "theMostDeaths": false,
            "theMostAssists": false,
            "theLowestNetworth": false,
            "noKills": false,
            "isBoughtBackBefore30": false
        },
        {
            "name": "TIMS",
            "steamId": 76561198115760109,
            "kills": 0,
            "deaths": 6,
            "assists": 5,
            "selectedHeroId": 27,
            "pickOrder": 6,
            "teamfightParticipation": 0.5,
            "heroTierDotaPlus": 39740,
            "firstBloodClaimed": false,
            "runes": 2,
            "gpm": 277.48828,
            "teamNum": 3,
            "isWon": false,
            "lastHits": 49,
            "towerKills": 1,
            "wardsPlaced": 6,
            "campsStacked": 5,
            "watchersTaken": 0,
            "smokesUsed": 2,
            "lotusesGrabbed": 3,
            "roshanKills": 0,
            "stuns": 45.19991,
            "tormentorKills": 0,
            "courierKills": 2,
            "networth": 8195,
            "madstonesCollected": 25,
            "isFirstPick": false,
            "isLastPick": false,
            "isMasterGrandMaster": false,
            "lastGameOfTheSeries": true,
            "theMostDeaths": true,
            "theMostAssists": false,
            "theLowestNetworth": false,
            "noKills": true,
            "isBoughtBackBefore30": false
        },
        {
            "name": "JACKBOYS",
            "steamId": 76561198352830965,
            "kills": 2,
            "deaths": 4,
            "assists": 3,
            "selectedHeroId": 18,
            "pickOrder": 1,
            "teamfightParticipation": 0.5,
            "heroTierDotaPlus": 39270,
            "firstBloodClaimed": false,
            "runes": 2,
            "gpm": 586.7718,
            "teamNum": 3,
            "isWon": false,
            "lastHits": 337,
            "towerKills": 0,
            "wardsPlaced": 1,
            "campsStacked": 1,
            "watchersTaken": 0,
            "smokesUsed": 0,
            "lotusesGrabbed": 0,
            "roshanKills": 0,
            "stuns": 21.466068,
            "tormentorKills": 0,
            "courierKills": 0,
            "networth": 17329,
            "madstonesCollected": 25,
            "isFirstPick": true,
            "isLastPick": false,
            "isMasterGrandMaster": false,
            "lastGameOfTheSeries": true,
            "theMostDeaths": false,
            "theMostAssists": false,
            "theLowestNetworth": false,
            "noKills": false,
            "isBoughtBackBefore30": false
        },
        {
            "name": "Armel",
            "steamId": 76561198124797733,
            "kills": 4,
            "deaths": 5,
            "assists": 4,
            "selectedHeroId": 106,
            "pickOrder": 2,
            "teamfightParticipation": 0.8,
            "heroTierDotaPlus": 72050,
            "firstBloodClaimed": false,
            "runes": 6,
            "gpm": 435.8547,
            "teamNum": 3,
            "isWon": false,
            "lastHits": 193,
            "towerKills": 0,
            "wardsPlaced": 1,
            "campsStacked": 0,
            "watchersTaken": 0,
            "smokesUsed": 0,
            "lotusesGrabbed": 0,
            "roshanKills": 0,
            "stuns": 60.665367,
            "tormentorKills": 0,
            "courierKills": 0,
            "networth": 12872,
            "madstonesCollected": 25,
            "isFirstPick": false,
            "isLastPick": false,
            "isMasterGrandMaster": true,
            "lastGameOfTheSeries": true,
            "theMostDeaths": false,
            "theMostAssists": false,
            "theLowestNetworth": false,
            "noKills": false,
            "isBoughtBackBefore30": false
        },
        {
            "name": "Jaunuel",
            "steamId": 76561198108792701,
            "kills": 2,
            "deaths": 5,
            "assists": 6,
            "selectedHeroId": 75,
            "pickOrder": 5,
            "teamfightParticipation": 0.8,
            "heroTierDotaPlus": 11170,
            "firstBloodClaimed": false,
            "runes": 4,
            "gpm": 257.7475,
            "teamNum": 3,
            "isWon": false,
            "lastHits": 16,
            "towerKills": 0,
            "wardsPlaced": 6,
            "campsStacked": 2,
            "watchersTaken": 0,
            "smokesUsed": 4,
            "lotusesGrabbed": 0,
            "roshanKills": 0,
            "stuns": 0.0,
            "tormentorKills": 0,
            "courierKills": 0,
            "networth": 7612,
            "madstonesCollected": 25,
            "isFirstPick": false,
            "isLastPick": false,
            "isMasterGrandMaster": false,
            "lastGameOfTheSeries": true,
            "theMostDeaths": false,
            "theMostAssists": false,
            "theLowestNetworth": true,
            "noKills": false,
            "isBoughtBackBefore30": false
        }
    ]
}