{
    "gameTimeSeconds": 2337.4333,
    "gameWinner": 2,
    "fbBeforeHorn": false,
    "fbAfter10min": false,
    "isRampageInGame": false,
    "lessThan25min": false,
    "leagueId": 17418,
    "playerInfo": [
        {
            "name": "Roselia",
            "steamId": 76561198280517752,
            "kills": 10,
            "deaths": 4,
            "assists": 10,
            "selectedHeroId": 53,
            "pickOrder": 5,
            "teamfightParticipation": 0.7407407,
            "heroTierDotaPlus": 23190,
            "firstBloodClaimed": true,
            "runes": 1,
            "gpm": 882.9942,
            "teamNum": 2,
            "isWon": true,
            "lastHits": 523,
            "towerKills": 10,
            "wardsPlaced": 0,
            "campsStacked": 1,
            "watchersTaken": 0,
            "smokesUsed": 0,
            "lotusesGrabbed": 1,
            "roshanKills": 1,
            "stuns": 0.0,
            "tormentorKills": 2,
            "courierKills": 0,
            "networth": 34399,
            "madstonesCollected": 35,
            "isFirstPick": false,
            "isLastPick": false,
            "isMasterGrandMaster": false,
            "lastGameOfTheSeries": true,
            "theMostDeaths": false,
            "theMostAssists": false,
            "theLowestNetworth": false,
            "noKills": false,
            "isBoughtBackBefore30": false
        },
        {
            "name": "NothingToSay",
            "steamId": 76561198134243802,
            "kills": 10,
            "deaths": 0,
            "assists": 16,
            "selectedHeroId": 120,
            "pickOrder": 2,
            "teamfightParticipation": 0.962963,
            "heroTierDotaPlus": 68785,
            "firstBloodClaimed": false,
            "runes": 19,
            "gpm": 606.8708,
            "teamNum": 2,
            "isWon": true,
            "lastHits": 284,
            "towerKills": 0,
            "wardsPlaced": 1,
            "campsStacked": 0,
            "watchersTaken": 3,
            "smokesUsed": 0,
            "lotusesGrabbed": 0,
            "roshanKills": 0,
            "stuns": 9.686229,
            "tormentorKills": 2,
            "courierKills": 0,
            "networth": 23642,
            "madstonesCollected": 31,
            "isFirstPick": true,
            "isLastPick": false,
            "isMasterGrandMaster": true,
            "lastGameOfTheSeries": true,
            "theMostDeaths": false,
            "theMostAssists": false,
            "theLowestNetworth": false,
            "noKills": false,
            "isBoughtBackBefore30": false
        },
        {
            "name": "Bach",
            "steamId": 76561198078399948,
            "kills": 2,
            "deaths": 1,
            "assists": 17,
            "selectedHeroId": 96,
            "pickOrder": 7,
            "teamfightParticipation": 0.7037037,
            "heroTierDotaPlus": 17040,
            "firstBloodClaimed": false,
            "runes": 1,
            "gpm": 521.2127,
            "teamNum": 2,
            "isWon": true,
            "lastHits": 295,
            "towerKills": 0,
            "wardsPlaced": 0,
            "campsStacked": 1,
            "watchersTaken": 4,
            "smokesUsed": 0,
            "lotusesGrabbed": 1,
            "roshanKills": 0,
            "stuns": 54.967308,
            "tormentorKills": 0,
            "courierKills": 1,
            "networth": 20305,
            "madstonesCollected": 34,
            "isFirstPick": false,
            "isLastPick": false,
            "isMasterGrandMaster": false,
            "lastGameOfTheSeries": true,
            "theMostDeaths": false,
            "theMostAssists": true,
            "theLowestNetworth": false,
            "noKills": false,
            "isBoughtBackBefore30": false
        },
        {
            "name": "镜",
            "steamId": 76561198111227295,
            "kills": 2,
            "deaths": 4,
            "assists": 17,
            "selectedHeroId": 90,
            "pickOrder": 6,
            "teamfightParticipation": 0.7037037,
            "heroTierDotaPlus": 28735,
            "firstBloodClaimed": false,
            "runes": 2,
            "gpm": 411.34863,
            "teamNum": 2,
            "isWon": true,
            "lastHits": 96,
            "towerKills": 0,
            "wardsPlaced": 3,
            "campsStacked": 5,
            "watchersTaken": 7,
            "smokesUsed": 4,
            "lotusesGrabbed": 0,
            "roshanKills": 0,
            "stuns": 0.0,
            "tormentorKills": 2,
            "courierKills": 1,
            "networth": 16025,
            "madstonesCollected": 28,
            "isFirstPick": false,
            "isLastPick": false,
            "isMasterGrandMaster": false,
            "lastGameOfTheSeries": true,
            "theMostDeaths": false,
            "theMostAssists": true,
            "theLowestNetworth": false,
            "noKills": false,
            "isBoughtBackBefore30": false
        },
        {
            "name": "May thy knife chip and shatter",
            "steamId": 76561198071380415,
            "kills": 3,
            "deaths": 5,
            "assists": 16,
            "selectedHeroId": 75,
            "pickOrder": 8,
            "teamfightParticipation": 0.6666667,
            "heroTierDotaPlus": 23335,
            "firstBloodClaimed": false,
            "runes": 0,
            "gpm": 309.62167,
            "teamNum": 2,
            "isWon": true,
            "lastHits": 39,
            "towerKills": 0,
            "wardsPlaced": 15,
            "campsStacked": 3,
            "watchersTaken": 12,
            "smokesUsed": 3,
            "lotusesGrabbed": 2,
            "roshanKills": 0,
            "stuns": 0.0,
            "tormentorKills": 2,
            "courierKills": 1,
            "networth": 12062,
            "madstonesCollected": 28,
            "isFirstPick": false,
            "isLastPick": false,
            "isMasterGrandMaster": false,
            "lastGameOfTheSeries": true,
            "theMostDeaths": false,
            "theMostAssists": false,
            "theLowestNetworth": false,
            "noKills": false,
            "isBoughtBackBefore30": false
        },
        {
            "name": "Ame",
            "steamId": 76561198859019881,
            "kills": 3,
            "deaths": 5,
            "assists": 2,
            "selectedHeroId": 70,
            "pickOrder": 4,
            "teamfightParticipation": 0.35714287,
            "heroTierDotaPlus": 38340,
            "firstBloodClaimed": false,
            "runes": 1,
            "gpm": 579.89246,
            "teamNum": 3,
            "isWon": false,
            "lastHits": 377,
            "towerKills": 0,
            "wardsPlaced": 0,
            "campsStacked": 2,
            "watchersTaken": 5,
            "smokesUsed": 0,
            "lotusesGrabbed": 6,
            "roshanKills": 0,
            "stuns": 6.7666483,
            "tormentorKills": 0,
            "courierKills": 0,
            "networth": 22591,
            "madstonesCollected": 35,
            "isFirstPick": false,
            "isLastPick": false,
            "isMasterGrandMaster": false,
            "lastGameOfTheSeries": true,
            "theMostDeaths": false,
            "theMostAssists": false,
            "theLowestNetworth": false,
            "noKills": false,
            "isBoughtBackBefore30": false
        },
        {
            "name": "Xm",
            "steamId": 76561198097395311,
            "kills": 5,
            "deaths": 5,
            "assists": 4,
            "selectedHeroId": 19,
            "pickOrder": 3,
            "teamfightParticipation": 0.64285713,
            "heroTierDotaPlus": 25340,
            "firstBloodClaimed": false,
            "runes": 12,
            "gpm": 443.38376,
            "teamNum": 3,
            "isWon": false,
            "lastHits": 243,
            "towerKills": 0,
            "wardsPlaced": 2,
            "campsStacked": 2,
            "watchersTaken": 4,
            "smokesUsed": 0,
            "lotusesGrabbed": 0,
            "roshanKills": 0,
            "stuns": 57.79488,
            "tormentorKills": 0,
            "courierKills": 1,
            "networth": 17273,
            "madstonesCollected": 31,
            "isFirstPick": false,
            "isLastPick": false,
            "isMasterGrandMaster": false,
            "lastGameOfTheSeries": true,
            "theMostDeaths": false,
            "theMostAssists": false,
            "theLowestNetworth": false,
            "noKills": false,
            "isBoughtBackBefore30": false
        },
        {
            "name": "Xxs",
            "steamId": 76561198090224486,
            "kills": 4,
            "deaths": 2,
            "assists": 7,
            "selectedHeroId": 55,
            "pickOrder": 9,
            "teamfightParticipation": 0.71428573,
            "heroTierDotaPlus": 17350,
            "firstBloodClaimed": false,
            "runes": 3,
            "gpm": 544.7257,
            "teamNum": 3,
            "isWon": false,
            "lastHits": 335,
            "towerKills": 1,
            "wardsPlaced": 0,
            "campsStacked": 5,
            "watchersTaken": 4,
            "smokesUsed": 0,
            "lotusesGrabbed": 0,
            "roshanKills": 1,
            "stuns": 10.232398,
            "tormentorKills": 0,
            "courierKills": 0,
            "networth": 21221,
            "madstonesCollected": 34,
            "isFirstPick": false,
            "isLastPick": false,
            "isMasterGrandMaster": false,
            "lastGameOfTheSeries": true,
            "theMostDeaths": false,
            "theMostAssists": false,
            "theLowestNetworth": false,
            "noKills": false,
            "isBoughtBackBefore30": false
        },
        {
            "name": "XinQ",
            "steamId": 76561198117741251,
            "kills": 0,
            "deaths": 8,
            "assists": 11,
            "selectedHeroId": 32,
            "pickOrder": 1,
            "teamfightParticipation": 0.78571427,
            "heroTierDotaPlus": 18335,
            "firstBloodClaimed": false,
            "runes": 2,
            "gpm": 269.80878,
            "teamNum": 3,
            "isWon": false,
            "lastHits": 71,
            "towerKills": 0,
            "wardsPlaced": 6,
            "campsStacked": 2,
            "watchersTaken": 8,
            "smokesUsed": 1,
            "lotusesGrabbed": 8,
            "roshanKills": 0,
            "stuns": 22.0,
            "tormentorKills": 0,
            "courierKills": 2,
            "networth": 10511,
            "madstonesCollected": 28,
            "isFirstPick": true,
            "isLastPick": false,
            "isMasterGrandMaster": false,
            "lastGameOfTheSeries": true,
            "theMostDeaths": true,
            "theMostAssists": false,
            "theLowestNetworth": false,
            "noKills": true,
            "isBoughtBackBefore30": false
        },
        {
            "name": "poloson",
            "steamId": 76561198037170520,
            "kills": 2,
            "deaths": 7,
            "assists": 6,
            "selectedHeroId": 64,
            "pickOrder": 10,
            "teamfightParticipation": 0.5,
            "heroTierDotaPlus": 3899,
            "firstBloodClaimed": false,
            "runes": 4,
            "gpm": 246.16745,
            "teamNum": 3,
            "isWon": false,
            "lastHits": 64,
            "towerKills": 0,
            "wardsPlaced": 10,
            "campsStacked": 2,
            "watchersTaken": 7,
            "smokesUsed": 6,
            "lotusesGrabbed": 1,
            "roshanKills": 0,
            "stuns": 53.46643,
            "tormentorKills": 0,
            "courierKills": 0,
            "networth": 9590,
            "madstonesCollected": 28,
            "isFirstPick": false,
            "isLastPick": true,
            "isMasterGrandMaster": false,
            "lastGameOfTheSeries": true,
            "theMostDeaths": false,
            "theMostAssists": false,
            "theLowestNetworth": true,
            "noKills": false,
            "isBoughtBackBefore30": false
        }
    ]
}